LICENSE
MANIFEST.in
README.md
VERSION_NOTES.txt
onerad.dat
setup.cfg
setup.py
LovelacePM/__init__.py
LovelacePM/aerodynamic_output.py
LovelacePM/aircraft.py
LovelacePM/atr_emp.dat
LovelacePM/atr_foil.dat
LovelacePM/atr_rud.dat
LovelacePM/body.py
LovelacePM/control.py
LovelacePM/documentation.py
LovelacePM/monoplane.py
LovelacePM/multiprocess_guard.py
LovelacePM/n0012.dat
LovelacePM/n4412.dat
LovelacePM/n65415.dat
LovelacePM/onerad.dat
LovelacePM/paneller.py
LovelacePM/pyfdyn.py
LovelacePM/pytoolkit.py
LovelacePM/sd7062.dat
LovelacePM/testcase_airfoil.py
LovelacePM/testcase_cilynder.py
LovelacePM/testcase_control.py
LovelacePM/testcase_fullconfig.py
LovelacePM/testcase_n0012_AR20.py
LovelacePM/testcase_n0012_rotating.py
LovelacePM/testcase_n65415.py
LovelacePM/testcase_oneram6.py
LovelacePM/testcase_plate.py
LovelacePM/testcase_random.py
LovelacePM/testcase_sd7062.py
LovelacePM/testcase_sphere.py
LovelacePM/testcase_wingonly_fullconfig.py
LovelacePM/utils.py
LovelacePM/wing.py
LovelacePM/xfoil_visc.py
LovelacePM.egg-info/PKG-INFO
LovelacePM.egg-info/SOURCES.txt
LovelacePM.egg-info/dependency_links.txt
LovelacePM.egg-info/requires.txt
LovelacePM.egg-info/top_level.txt