Metadata-Version: 2.1
Name: LovelacePM
Version: 0.2.5
Summary: Python based, open source vortex ring panel method code
Home-page: https://github.com/pedrosecchi67/LovelacePM
Author: Pedro de Almeida Secchi
Author-email: pedrosecchimail@gmail.com
License: UNKNOWN
Platform: UNKNOWN
Classifier: Programming Language :: Python :: 3
Classifier: License :: OSI Approved :: GNU General Public License (GPL)
Classifier: Operating System :: OS Independent
Requires-Python: >=3.6
